livecsv/__init__.py
livecsv/driver.py
livecsv-0.41.dist-info/LICENSE
livecsv-0.41.dist-info/METADATA
livecsv-0.41.dist-info/WHEEL
livecsv-0.41.dist-info/entry_points.txt
livecsv-0.41.dist-info/top_level.txt
livecsv-0.41.dist-info/RECORD
