Metadata-Version: 2.2
Name: livecsv
Version: 0.41
Summary: A custom SQLAlchemy dialect to load CSV from the web (using DuckDB for caching)
Author-email: Eyal Rahmani <eyal.rahmani@med.uni-heidelberg.de>
Maintainer-email: Eyal Rahmani <eyal.rahmani@med.uni-heidelberg.de>
License: MIT License
Project-URL: Homepage, https://github.com/eyal-erknet/livecsv
Project-URL: Repository, https://github.com/eyal-erknet/livecsv.git
Keywords: sqlalchemy,sql,csv,duckdb
Classifier: Development Status :: 4 - Beta
Classifier: Intended Audience :: Developers
Classifier: Programming Language :: Python :: 3
Classifier: Operating System :: OS Independent
Requires-Python: >=3.8
License-File: LICENSE
Requires-Dist: SQLAlchemy
Requires-Dist: duckdb
Requires-Dist: duckdb_engine
